pylcp/__init__.py
pylcp/atom.py
pylcp/common.py
pylcp/fields.py
pylcp/governingeq.py
pylcp/gratings.py
pylcp/hamiltonian.py
pylcp/heuristiceq.py
pylcp/integration_tools.py
pylcp/obe.py
pylcp/rateeq.py
pylcp/hamiltonians/XFmolecules.py
pylcp/hamiltonians/__init__.py
pylcp-1.0.2.dist-info/LICENSE
pylcp-1.0.2.dist-info/METADATA
pylcp-1.0.2.dist-info/WHEEL
pylcp-1.0.2.dist-info/top_level.txt
pylcp-1.0.2.dist-info/RECORD
